finance_calculator_sk24/__init__.py
finance_calculator_sk24/__main__.py
finance_calculator_sk24/calculator.py
finance_calculator_sk24-0.1.dist-info/METADATA
finance_calculator_sk24-0.1.dist-info/WHEEL
finance_calculator_sk24-0.1.dist-info/entry_points.txt
finance_calculator_sk24-0.1.dist-info/top_level.txt
finance_calculator_sk24-0.1.dist-info/RECORD
